{
  "mara": [
    {
      "Loc": "guinee",
      "Value": 6,
      "ISO-3": "GIN"
    },
    {
      "Loc": "france",
      "Value": 5,
      "ISO-3": "FRA"
    },
    {
      "Loc": "afghanistan",
      "Value": 1,
      "ISO-3": "AFG"
    },
    {
      "Loc": "russie",
      "Value": 1,
      "ISO-3": "RUS"
    }
  ],
  "kone": [
    {
      "Loc": "guinee",
      "Value": 3,
      "ISO-3": "GIN"
    },
    {
      "Loc": "niger",
      "Value": 1,
      "ISO-3": "NER"
    },
    {
      "Loc": "senegal",
      "Value": 1,
      "ISO-3": "SEN"
    },
    {
      "Loc": "france",
      "Value": 1,
      "ISO-3": "FRA"
    },
    {
      "Loc": "nigeria",
      "Value": 2,
      "ISO-3": "NGA"
    },
    {
      "Loc": "ghana",
      "Value": 1,
      "ISO-3": "GHA"
    },
    {
      "Loc": "benin",
      "Value": 1,
      "ISO-3": "BEN"
    },
    {
      "Loc": "togo",
      "Value": 1,
      "ISO-3": "TGO"
    },
    {
      "Loc": "canada",
      "Value": 1,
      "ISO-3": "CAN"
    }
  ],
  "macron": [
    {
      "Loc": "france",
      "Value": 85,
      "ISO-3": "FRA"
    },
    {
      "Loc": "guinee",
      "Value": 57,
      "ISO-3": "GIN"
    },
    {
      "Loc": "turquie",
      "Value": 7,
      "ISO-3": "TUR"
    },
    {
      "Loc": "canada",
      "Value": 35,
      "ISO-3": "CAN"
    },
    {
      "Loc": "iran",
      "Value": 1,
      "ISO-3": "IRN"
    },
    {
      "Loc": "koweit",
      "Value": 1,
      "ISO-3": "KWT"
    },
    {
      "Loc": "jordanie",
      "Value": 1,
      "ISO-3": "JOR"
    },
    {
      "Loc": "qatar",
      "Value": 1,
      "ISO-3": "QAT"
    },
    {
      "Loc": "niger",
      "Value": 19,
      "ISO-3": "NER"
    },
    {
      "Loc": "syrie",
      "Value": 2,
      "ISO-3": "SYR"
    },
    {
      "Loc": "liban",
      "Value": 1,
      "ISO-3": "LBN"
    },
    {
      "Loc": "algerie",
      "Value": 19,
      "ISO-3": "DZA"
    },
    {
      "Loc": "mauritanie",
      "Value": 5,
      "ISO-3": "MRT"
    },
    {
      "Loc": "etatsunis",
      "Value": 13,
      "ISO-3": "USA"
    },
    {
      "Loc": "italie",
      "Value": 3,
      "ISO-3": "ITA"
    },
    {
      "Loc": "burkina faso",
      "Value": 16,
      "ISO-3": "BFA"
    },
    {
      "Loc": "maroc",
      "Value": 3,
      "ISO-3": "MAR"
    },
    {
      "Loc": "libye",
      "Value": 12,
      "ISO-3": "LBY"
    },
    {
      "Loc": "grece",
      "Value": 3,
      "ISO-3": "GRC"
    },
    {
      "Loc": "russie",
      "Value": 18,
      "ISO-3": "RUS"
    },
    {
      "Loc": "senegal",
      "Value": 4,
      "ISO-3": "SEN"
    },
    {
      "Loc": "nigeria",
      "Value": 4,
      "ISO-3": "NGA"
    },
    {
      "Loc": "togo",
      "Value": 4,
      "ISO-3": "TGO"
    },
    {
      "Loc": "chine",
      "Value": 6,
      "ISO-3": "CHN"
    },
    {
      "Loc": "inde",
      "Value": 1,
      "ISO-3": "IND"
    },
    {
      "Loc": "venezuela",
      "Value": 1,
      "ISO-3": "VEN"
    },
    {
      "Loc": "cuba",
      "Value": 1,
      "ISO-3": "CUB"
    },
    {
      "Loc": "rwanda",
      "Value": 1,
      "ISO-3": "RWA"
    },
    {
      "Loc": "tchad",
      "Value": 13,
      "ISO-3": "TCD"
    },
    {
      "Loc": "tunisie",
      "Value": 2,
      "ISO-3": "TUN"
    },
    {
      "Loc": "autriche",
      "Value": 1,
      "ISO-3": "AUT"
    },
    {
      "Loc": "pologne",
      "Value": 1,
      "ISO-3": "POL"
    },
    {
      "Loc": "australie",
      "Value": 3,
      "ISO-3": "AUS"
    },
    {
      "Loc": "afghanistan",
      "Value": 1,
      "ISO-3": "AFG"
    },
    {
      "Loc": "royaumeuni",
      "Value": 1,
      "ISO-3": "GBR"
    }
  ],
  "barkhane": [
    {
      "Loc": "niger",
      "Value": 8,
      "ISO-3": "NER"
    },
    {
      "Loc": "libye",
      "Value": 1,
      "ISO-3": "LBY"
    },
    {
      "Loc": "algerie",
      "Value": 3,
      "ISO-3": "DZA"
    },
    {
      "Loc": "guinee",
      "Value": 26,
      "ISO-3": "GIN"
    },
    {
      "Loc": "burkina faso",
      "Value": 9,
      "ISO-3": "BFA"
    },
    {
      "Loc": "france",
      "Value": 24,
      "ISO-3": "FRA"
    },
    {
      "Loc": "tchad",
      "Value": 5,
      "ISO-3": "TCD"
    },
    {
      "Loc": "canada",
      "Value": 10,
      "ISO-3": "CAN"
    },
    {
      "Loc": "afghanistan",
      "Value": 1,
      "ISO-3": "AFG"
    },
    {
      "Loc": "russie",
      "Value": 4,
      "ISO-3": "RUS"
    },
    {
      "Loc": "etatsunis",
      "Value": 2,
      "ISO-3": "USA"
    },
    {
      "Loc": "espagne",
      "Value": 1,
      "ISO-3": "ESP"
    }
  ],
  "keita": [
    {
      "Loc": "guinee",
      "Value": 34,
      "ISO-3": "GIN"
    },
    {
      "Loc": "france",
      "Value": 17,
      "ISO-3": "FRA"
    },
    {
      "Loc": "italie",
      "Value": 1,
      "ISO-3": "ITA"
    },
    {
      "Loc": "maroc",
      "Value": 2,
      "ISO-3": "MAR"
    },
    {
      "Loc": "burkina faso",
      "Value": 4,
      "ISO-3": "BFA"
    },
    {
      "Loc": "niger",
      "Value": 2,
      "ISO-3": "NER"
    },
    {
      "Loc": "mauritanie",
      "Value": 2,
      "ISO-3": "MRT"
    },
    {
      "Loc": "algerie",
      "Value": 3,
      "ISO-3": "DZA"
    },
    {
      "Loc": "tchad",
      "Value": 3,
      "ISO-3": "TCD"
    },
    {
      "Loc": "etatsunis",
      "Value": 3,
      "ISO-3": "USA"
    },
    {
      "Loc": "canada",
      "Value": 2,
      "ISO-3": "CAN"
    },
    {
      "Loc": "senegal",
      "Value": 3,
      "ISO-3": "SEN"
    },
    {
      "Loc": "inde",
      "Value": 3,
      "ISO-3": "IND"
    },
    {
      "Loc": "cameroun",
      "Value": 1,
      "ISO-3": "CMR"
    },
    {
      "Loc": "australie",
      "Value": 1,
      "ISO-3": "AUS"
    },
    {
      "Loc": "irak",
      "Value": 1,
      "ISO-3": "IRQ"
    },
    {
      "Loc": "venezuela",
      "Value": 1,
      "ISO-3": "VEN"
    },
    {
      "Loc": "cuba",
      "Value": 1,
      "ISO-3": "CUB"
    },
    {
      "Loc": "colombie",
      "Value": 1,
      "ISO-3": "COL"
    },
    {
      "Loc": "chine",
      "Value": 1,
      "ISO-3": "CHN"
    },
    {
      "Loc": "pakistan",
      "Value": 1,
      "ISO-3": "PAK"
    },
    {
      "Loc": "mexique",
      "Value": 1,
      "ISO-3": "MEX"
    },
    {
      "Loc": "pologne",
      "Value": 1,
      "ISO-3": "POL"
    },
    {
      "Loc": "tunisie",
      "Value": 1,
      "ISO-3": "TUN"
    },
    {
      "Loc": "autriche",
      "Value": 1,
      "ISO-3": "AUT"
    },
    {
      "Loc": "syrie",
      "Value": 2,
      "ISO-3": "SYR"
    },
    {
      "Loc": "armenie",
      "Value": 1,
      "ISO-3": "ARM"
    },
    {
      "Loc": "belarus",
      "Value": 1,
      "ISO-3": "BLR"
    },
    {
      "Loc": "afghanistan",
      "Value": 1,
      "ISO-3": "AFG"
    },
    {
      "Loc": "russie",
      "Value": 4,
      "ISO-3": "RUS"
    },
    {
      "Loc": "togo",
      "Value": 2,
      "ISO-3": "TGO"
    }
  ],
  "ibk": [
    {
      "Loc": "guinee",
      "Value": 21,
      "ISO-3": "GIN"
    },
    {
      "Loc": "france",
      "Value": 4,
      "ISO-3": "FRA"
    },
    {
      "Loc": "italie",
      "Value": 1,
      "ISO-3": "ITA"
    },
    {
      "Loc": "turquie",
      "Value": 1,
      "ISO-3": "TUR"
    },
    {
      "Loc": "ghana",
      "Value": 1,
      "ISO-3": "GHA"
    },
    {
      "Loc": "maroc",
      "Value": 1,
      "ISO-3": "MAR"
    },
    {
      "Loc": "senegal",
      "Value": 5,
      "ISO-3": "SEN"
    },
    {
      "Loc": "niger",
      "Value": 1,
      "ISO-3": "NER"
    },
    {
      "Loc": "canada",
      "Value": 2,
      "ISO-3": "CAN"
    },
    {
      "Loc": "algerie",
      "Value": 1,
      "ISO-3": "DZA"
    },
    {
      "Loc": "tchad",
      "Value": 1,
      "ISO-3": "TCD"
    },
    {
      "Loc": "cameroun",
      "Value": 1,
      "ISO-3": "CMR"
    },
    {
      "Loc": "burkina faso",
      "Value": 1,
      "ISO-3": "BFA"
    }
  ],
  "paty": [
    {
      "Loc": "iran",
      "Value": 1,
      "ISO-3": "IRN"
    },
    {
      "Loc": "koweit",
      "Value": 1,
      "ISO-3": "KWT"
    },
    {
      "Loc": "france",
      "Value": 4,
      "ISO-3": "FRA"
    },
    {
      "Loc": "jordanie",
      "Value": 1,
      "ISO-3": "JOR"
    },
    {
      "Loc": "qatar",
      "Value": 1,
      "ISO-3": "QAT"
    },
    {
      "Loc": "canada",
      "Value": 1,
      "ISO-3": "CAN"
    },
    {
      "Loc": "australie",
      "Value": 1,
      "ISO-3": "AUS"
    },
    {
      "Loc": "irak",
      "Value": 1,
      "ISO-3": "IRQ"
    },
    {
      "Loc": "venezuela",
      "Value": 1,
      "ISO-3": "VEN"
    },
    {
      "Loc": "cuba",
      "Value": 1,
      "ISO-3": "CUB"
    },
    {
      "Loc": "colombie",
      "Value": 1,
      "ISO-3": "COL"
    },
    {
      "Loc": "etatsunis",
      "Value": 1,
      "ISO-3": "USA"
    },
    {
      "Loc": "inde",
      "Value": 2,
      "ISO-3": "IND"
    },
    {
      "Loc": "chine",
      "Value": 1,
      "ISO-3": "CHN"
    },
    {
      "Loc": "pakistan",
      "Value": 1,
      "ISO-3": "PAK"
    },
    {
      "Loc": "mexique",
      "Value": 1,
      "ISO-3": "MEX"
    },
    {
      "Loc": "guinee",
      "Value": 1,
      "ISO-3": "GIN"
    },
    {
      "Loc": "pologne",
      "Value": 1,
      "ISO-3": "POL"
    },
    {
      "Loc": "tunisie",
      "Value": 1,
      "ISO-3": "TUN"
    },
    {
      "Loc": "autriche",
      "Value": 1,
      "ISO-3": "AUT"
    },
    {
      "Loc": "syrie",
      "Value": 1,
      "ISO-3": "SYR"
    },
    {
      "Loc": "armenie",
      "Value": 1,
      "ISO-3": "ARM"
    },
    {
      "Loc": "belarus",
      "Value": 1,
      "ISO-3": "BLR"
    }
  ],
  "tall": [
    {
      "Loc": "guinee",
      "Value": 1,
      "ISO-3": "GIN"
    }
  ],
  "walker": [
    {
      "Loc": "canada",
      "Value": 2,
      "ISO-3": "CAN"
    },
    {
      "Loc": "mexique",
      "Value": 1,
      "ISO-3": "MEX"
    },
    {
      "Loc": "paraguay",
      "Value": 1,
      "ISO-3": "PRY"
    },
    {
      "Loc": "france",
      "Value": 1,
      "ISO-3": "FRA"
    },
    {
      "Loc": "venezuela",
      "Value": 2,
      "ISO-3": "VEN"
    },
    {
      "Loc": "cuba",
      "Value": 2,
      "ISO-3": "CUB"
    },
    {
      "Loc": "etatsunis",
      "Value": 1,
      "ISO-3": "USA"
    },
    {
      "Loc": "russie",
      "Value": 1,
      "ISO-3": "RUS"
    },
    {
      "Loc": "chine",
      "Value": 1,
      "ISO-3": "CHN"
    }
  ],
  "louadj": [
    {
      "Loc": "russie",
      "Value": 18,
      "ISO-3": "RUS"
    },
    {
      "Loc": "chine",
      "Value": 14,
      "ISO-3": "CHN"
    },
    {
      "Loc": "etatsunis",
      "Value": 17,
      "ISO-3": "USA"
    },
    {
      "Loc": "algerie",
      "Value": 11,
      "ISO-3": "DZA"
    },
    {
      "Loc": "canada",
      "Value": 3,
      "ISO-3": "CAN"
    },
    {
      "Loc": "guinee",
      "Value": 17,
      "ISO-3": "GIN"
    },
    {
      "Loc": "france",
      "Value": 19,
      "ISO-3": "FRA"
    },
    {
      "Loc": "burkina faso",
      "Value": 6,
      "ISO-3": "BFA"
    },
    {
      "Loc": "tchad",
      "Value": 7,
      "ISO-3": "TCD"
    },
    {
      "Loc": "niger",
      "Value": 10,
      "ISO-3": "NER"
    },
    {
      "Loc": "turquie",
      "Value": 4,
      "ISO-3": "TUR"
    },
    {
      "Loc": "libye",
      "Value": 10,
      "ISO-3": "LBY"
    },
    {
      "Loc": "australie",
      "Value": 3,
      "ISO-3": "AUS"
    },
    {
      "Loc": "maroc",
      "Value": 7,
      "ISO-3": "MAR"
    },
    {
      "Loc": "afghanistan",
      "Value": 6,
      "ISO-3": "AFG"
    },
    {
      "Loc": "syrie",
      "Value": 5,
      "ISO-3": "SYR"
    },
    {
      "Loc": "irak",
      "Value": 3,
      "ISO-3": "IRQ"
    },
    {
      "Loc": "royaumeuni",
      "Value": 6,
      "ISO-3": "GBR"
    },
    {
      "Loc": "soudan",
      "Value": 4,
      "ISO-3": "SDN"
    },
    {
      "Loc": "iran",
      "Value": 4,
      "ISO-3": "IRN"
    },
    {
      "Loc": "espagne",
      "Value": 1,
      "ISO-3": "ESP"
    },
    {
      "Loc": "inde",
      "Value": 3,
      "ISO-3": "IND"
    },
    {
      "Loc": "mexique",
      "Value": 3,
      "ISO-3": "MEX"
    },
    {
      "Loc": "yemen",
      "Value": 1,
      "ISO-3": "YEM"
    },
    {
      "Loc": "israel",
      "Value": 1,
      "ISO-3": "ISR"
    },
    {
      "Loc": "tunisie",
      "Value": 3,
      "ISO-3": "TUN"
    },
    {
      "Loc": "grece",
      "Value": 1,
      "ISO-3": "GRC"
    },
    {
      "Loc": "nigeria",
      "Value": 3,
      "ISO-3": "NGA"
    },
    {
      "Loc": "ethiopie",
      "Value": 1,
      "ISO-3": "ETH"
    },
    {
      "Loc": "italie",
      "Value": 1,
      "ISO-3": "ITA"
    },
    {
      "Loc": "taiwan",
      "Value": 1,
      "ISO-3": "TWN"
    },
    {
      "Loc": "mauritanie",
      "Value": 2,
      "ISO-3": "MRT"
    },
    {
      "Loc": "senegal",
      "Value": 1,
      "ISO-3": "SEN"
    }
  ]
}